conanapi/ConanAPI.py
conanapi/__init__.py
conanapi/commands/ConfigSubCommand.py
conanapi/commands/DownloadCommand.py
conanapi/commands/EditableSubCommand.py
conanapi/commands/InspectCommand.py
conanapi/commands/SearchCommand.py
conanapi/commands/UploadCommand.py
conanapi/commands/__init__.py
conanapi/internal/Utilities.py
conanapi/internal/__init__.py
conanapi/types/LockFile.py
conanapi/types/Reference.py
conanapi/types/__init__.py
conex/ConexAPI.py
conex/__init__.py
conex/cli.py
conex/cli_parsers/ArgumentParser.py
conex/cli_parsers/ConfigCommandParser.py
conex/cli_parsers/DebugParser.py
conex/cli_parsers/DownloadCommandParser.py
conex/cli_parsers/EditableCommandParser.py
conex/cli_parsers/MigrateCommandParser.py
conex/cli_parsers/UploadCommandParser.py
conex/cli_parsers/__init__.py
conex/commands/ConfigSubCommand.py
conex/commands/DownloadCommand.py
conex/commands/EditableSubCommand.py
conex/commands/MigrateCommand.py
conex/commands/UploadCommand.py
conex/commands/__init__.py
conex/exceptions/__init__.py
conex/internal/Utilities.py
conex/internal/__init__.py
conex/internal/fakes/FakeConanAPI.py
conex/internal/fakes/__init__.py
conex-0.3.0.dist-info/METADATA
conex-0.3.0.dist-info/WHEEL
conex-0.3.0.dist-info/entry_points.txt
conex-0.3.0.dist-info/RECORD
